Workbook

Sheet Summary
A1: Expo group expense summary
A2: Description | B2: Amount(BDT) | C2: Total project cost | D2: Received amount | E2: Balance
A3: Total Contactor payment | B3: ='Contactors payment'!F22 -> 11483
A4: Total material cost | B4: ='material cost'!F16 -> 459724
A5: Total site expense and convence | B5: ='Site expense and convence'!D10 -> 13543
A6: Office overhead | B6: ='office overhead'!E4 -> 68632 | C6: =SUM(B3:B6) -> 553382 | D6: ='Received amount'!C7 -> 1933678 | E6: =(D6-C6) -> 1380296

Sheet Contactors payment
A1: Contactor payment
A2: Name | B2: Date | C2: Payment | D2: Cumulative payment | E2: contactors total | F2: All contactor total
B3: 46027 | C3: 548 | D3: ='Contactors payment'!C3 -> 548
B4: 46058 | C4: 400 | D4: =D3+C4 -> 948
B5: 46086 | C5: 400 | D5: =D4+C5 -> 1348
B6: 46117 | C6: 750 | D6: =D5+C6 -> 2098
A7: Wood contactor (X) | B7: 46178 | C7: 700 | D7: =D6+C7 -> 2798
B8: 46208 | C8: 1000 | D8: =D7+C8 -> 3798 | E8: =D8 -> 3798
B10: 46058 | C10: 647 | D10: ='Contactors payment'!C10 -> 647
B11: 46086 | C11: 300 | D11: =D10+C11 -> 947
B12: 46117 | C12: 100 | D12: =D11+C12 -> 1047
A13: Electricity contactor (Y) | B13: 46147 | C13: 200 | D13: =D12+C13 -> 1247
B14: 46178 | C14: 600 | D14: =D13+C14 -> 1847 | E14: =D14 -> 1847
B16: 46058 | C16: 350 | D16: ='Contactors payment'!C16 -> 350
B17: 46117 | C17: 300 | D17: =D16+C17 -> 650
B18: 46147 | C18: 400 | D18: =D17+C18 -> 1050
A19: Sanitary contactor (Z) | B19: 46178 | C19: 300 | D19: =D18+C19 -> 1350
B20: 46208 | C20: 600 | D20: =D19+C20 -> 1950
B21: 46239 | C21: 200 | D21: =D20+C21 -> 2150 | E21: =D21 -> 2150
F22: =(E8+E14+E21+E28+E35) -> 11483
B23: 46027 | C23: 240 | D23: ='Contactors payment'!C23 -> 240
B24: 46058 | C24: 300 | D24: =D23+C24 -> 540
B25: 46086 | C25: 400 | D25: =D24+C25 -> 940
A26: Tiles contactor (A) | B26: 46147 | C26: 700 | D26: =D25+C26 -> 1640
B27: 46178 | C27: 300 | D27: =D26+C27 -> 1940
B28: 46208 | C28: 200 | D28: =D27+C28 -> 2140 | E28: =D28 -> 2140
B30: 46027 | C30: 348 | D30: ='Contactors payment'!C30 -> 348
B31: 46058 | C31: 300 | D31: =D30+C31 -> 648
B32: 46086 | C32: 400 | D32: =D31+C32 -> 1048
A33: Paint contactor (B) | B33: 46178 | C33: 100 | D33: =D32+C33 -> 1148
B34: 46208 | C34: 200 | D34: =D33+C34 -> 1348
B35: 46239 | C35: 200 | D35: =D34+C35 -> 1548 | E35: =D35 -> 1548

Sheet material cost
A1: Material cost
A2: Name | B2: Date | C2: Amount | D2: Cumulative amount | E2: Item total | F2: All Item total
B3: 46027 | C3: 23456 | D3: ='material cost'!C3 -> 23456
B4: 46058 | C4: 13000 | D4: =(D3+C4) -> 36456
A5: Wood | B5: 46086 | C5: 10000 | D5: =(D4+C5) -> 46456
B6: 46117 | C6: 12345 | D6: =(D5+C6) -> 58801
B7: 46147 | C7: 10000 | D7: =(D6+C7) -> 68801 | E7: =D7 -> 68801
B9: 46027 | C9: 12345 | D9: ='material cost'!C9 -> 12345
B10: 46058 | C10: 20000 | D10: =(D9+C10) -> 32345
A11: Sanitary | B11: 46086 | C11: 20000 | D11: =(D10+C11) -> 52345
B12: 46117 | C12: 2000 | D12: =(D11+C12) -> 54345
B13: 46147 | C13: 3000 | D13: =(D12+C13) -> 57345 | E13: =D13 -> 57345
B15: 46027 | C15: 12345 | D15: ='material cost'!C15 -> 12345
B16: 46058 | C16: 23000 | D16: =(D15+C16) -> 35345 | F16: =(E7+E13+E19+E25+E31) -> 459724
A17: Tiles | B17: 46086 | C17: 13000 | D17: =(D16+C17) -> 48345
B18: 46117 | C18: 2000 | D18: =(D17+C18) -> 50345
B19: 46147 | C19: 3000 | D19: =(D18+C19) -> 53345 | E19: =D19 -> 53345
B21: 46027 | C21: 26543 | D21: ='material cost'!C21 -> 26543
B22: 46058 | C22: 21000 | D22: =(D21+C22) -> 47543
A23: Paint | B23: 46086 | C23: 23000 | D23: =(D22+C23) -> 70543
B24: 46117 | C24: 3000 | D24: =(D23+C24) -> 73543
B25: 46147 | C25: 20000 | D25: =(D24+C25) -> 93543 | E25: =D25 -> 93543
B27: 46027 | C27: 87690 | D27: ='material cost'!C27 -> 87690
B28: 46058 | C28: 20000 | D28: =(D27+C28) -> 107690
A29: Electricity | B29: 46086 | C29: 36000 | D29: =(D28+C29) -> 143690
B30: 46117 | C30: 22000 | D30: =(D29+C30) -> 165690
B31: 46147 | C31: 21000 | D31: =(D30+C31) -> 186690 | E31: =D31 -> 186690

Sheet Site expense and convence
A1: Site expense and convence
A2: Description | B2: Amount | C2: Cumulative amount | D2: Convence and others total
A3: X vai convence | B3: 2298 | C3: ='Site expense and convence'!B3 -> 2298
A4: y vai convence | B4: 3000 | C4: =(C3+B4) -> 5298
A5: z vai convence | B5: 3000 | C5: =(C4+B5) -> 8298
A6: a vai convence | B6: 2145 | C6: =(C5+B6) -> 10443
A7: b vai convence | B7: 2200 | C7: =(C6+B7) -> 12643
A8: x vai food bill | B8: 300 | C8: =(C7+B8) -> 12943
A9: z vai repair bill | B9: 400 | C9: =(C8+B9) -> 13343
A10: y vai repair bill | B10: 200 | C10: =(C9+B10) -> 13543 | D10: =C10 -> 13543

Sheet office overhead
A1: Office overhead
A2: Project Name | B2: Date | C2: Amount | D2: Cumulative amount | E2: Total amount
A3: Expo group | B3: 46027 | C3: 45632 | D3: ='office overhead'!C3 -> 45632
B4: 46058 | C4: 23000 | D4: =(D3+C4) -> 68632 | E4: =D4 -> 68632

Sheet Received amount
A1: Received amount
A2: Date | B2: Amount | C2: Total
A3: 46027 | B3: 345678
A4: 46058 | B4: 211000
A5: 46086 | B5: 467000
A6: 46117 | B6: 410000
A7: 46147 | B7: 500000 | C7: =SUM(B3:B7) -> 1933678

Sheet Updated balance
A1: Accounts Status
F2: 46117
A3: Date | B3: Description | C3: Desposit (Sir) | D3: Received Amount | E3: Expenses Amount | F3: Balance | G3: Reference | H3: Approval
F4: =D4 -> 0
F5: =+F4+D5-E5 -> 0
F6: =+F5+D6-E6 -> 0
F7: =+F6+D7-E7 -> 0
F8: =+F7+D8-E8 -> 0
F9: =+F8+D9-E9 -> 0
F10: =+F9+D10-E10 -> 0
F11: =+F10+D11-E11 -> 0
F12: =+F11+D12-E12 -> 0
F13: =+F12+D13-E13 -> 0
F14: =+F13+D14-E14 -> 0
F15: =+F14+D15-E15 -> 0
F16: =+F15+D16-E16 -> 0
... F45: =+F44+D45-E45 -> 0
A46: Total Cost | C46: =SUM(C4:C5) -> 0 | D46: =SUM(D4:D45) -> 0 | E46: =SUM(E5:E45) -> 0 | F46: =D46-E46 -> 0
